odoo/addons/website_sale_product_brand/README.rst
odoo/addons/website_sale_product_brand/__init__.py
odoo/addons/website_sale_product_brand/__manifest__.py
odoo/addons/website_sale_product_brand/controllers/__init__.py
odoo/addons/website_sale_product_brand/controllers/main.py
odoo/addons/website_sale_product_brand/data/website_menu.xml
odoo/addons/website_sale_product_brand/demo/assets.xml
odoo/addons/website_sale_product_brand/demo/product_brand_demo.xml
odoo/addons/website_sale_product_brand/demo/product_product_demo.xml
odoo/addons/website_sale_product_brand/i18n/ar.po
odoo/addons/website_sale_product_brand/i18n/bg.po
odoo/addons/website_sale_product_brand/i18n/bs.po
odoo/addons/website_sale_product_brand/i18n/ca.po
odoo/addons/website_sale_product_brand/i18n/cs.po
odoo/addons/website_sale_product_brand/i18n/da.po
odoo/addons/website_sale_product_brand/i18n/de.po
odoo/addons/website_sale_product_brand/i18n/el_GR.po
odoo/addons/website_sale_product_brand/i18n/en_GB.po
odoo/addons/website_sale_product_brand/i18n/es.po
odoo/addons/website_sale_product_brand/i18n/es_AR.po
odoo/addons/website_sale_product_brand/i18n/es_CL.po
odoo/addons/website_sale_product_brand/i18n/es_CO.po
odoo/addons/website_sale_product_brand/i18n/es_CR.po
odoo/addons/website_sale_product_brand/i18n/es_DO.po
odoo/addons/website_sale_product_brand/i18n/es_EC.po
odoo/addons/website_sale_product_brand/i18n/es_MX.po
odoo/addons/website_sale_product_brand/i18n/es_PE.po
odoo/addons/website_sale_product_brand/i18n/et.po
odoo/addons/website_sale_product_brand/i18n/eu.po
odoo/addons/website_sale_product_brand/i18n/fa.po
odoo/addons/website_sale_product_brand/i18n/fi.po
odoo/addons/website_sale_product_brand/i18n/fr.po
odoo/addons/website_sale_product_brand/i18n/he.po
odoo/addons/website_sale_product_brand/i18n/hr.po
odoo/addons/website_sale_product_brand/i18n/hr_HR.po
odoo/addons/website_sale_product_brand/i18n/hu.po
odoo/addons/website_sale_product_brand/i18n/id.po
odoo12_addon_website_sale_product_brand-12.0.1.3.1.dist-info/METADATA
odoo12_addon_website_sale_product_brand-12.0.1.3.1.dist-info/WHEEL
odoo12_addon_website_sale_product_brand-12.0.1.3.1.dist-info/top_level.txt
odoo12_addon_website_sale_product_brand-12.0.1.3.1.dist-info/RECORD
