Metadata-Version: 2.1
Name: odoo12-addon-website-sale-product-brand
Version: 12.0.1.3.1
Summary: Product Brand Filtering in Website
Home-page: https://github.com/OCA/e-commerce
Author: Serpent Consulting Services Pvt. Ltd., Tecnativa, Odoo Community Association (OCA)
Author-email: support@odoo-community.org
License: AGPL-3
Platform: UNKNOWN
Classifier: Programming Language :: Python
Classifier: Framework :: Odoo
Classifier: License :: OSI Approved :: GNU Affero General Public License v3
Requires-Python: >=3.5
Requires-Dist: odoo12-addon-product-brand
Requires-Dist: odoo (<12.1dev,>=12.0a)
